odoo/addons/stock_report_quantity_by_location/README.rst
odoo/addons/stock_report_quantity_by_location/__init__.py
odoo/addons/stock_report_quantity_by_location/__manifest__.py
odoo/addons/stock_report_quantity_by_location/i18n/es_MX.po
odoo/addons/stock_report_quantity_by_location/i18n/stock_report_quantity_by_location.pot
odoo/addons/stock_report_quantity_by_location/readme/CONTRIBUTORS.rst
odoo/addons/stock_report_quantity_by_location/readme/DESCRIPTION.rst
odoo/addons/stock_report_quantity_by_location/static/description/icon.png
odoo/addons/stock_report_quantity_by_location/static/description/index.html
odoo/addons/stock_report_quantity_by_location/tests/__init__.py
odoo/addons/stock_report_quantity_by_location/tests/test_stock_report_quantity_by_location.py
odoo/addons/stock_report_quantity_by_location/wizards/__init__.py
odoo/addons/stock_report_quantity_by_location/wizards/stock_report_quantity_by_location.py
odoo/addons/stock_report_quantity_by_location/wizards/stock_report_quantity_by_location_views.xml
odoo13_addon_stock_report_quantity_by_location-13.0.2.0.0.dist-info/METADATA
odoo13_addon_stock_report_quantity_by_location-13.0.2.0.0.dist-info/WHEEL
odoo13_addon_stock_report_quantity_by_location-13.0.2.0.0.dist-info/top_level.txt
odoo13_addon_stock_report_quantity_by_location-13.0.2.0.0.dist-info/RECORD
